deteksi_gempa/__init__.py
indonesian.BMKG-0.17.dist-info/LICENSE
indonesian.BMKG-0.17.dist-info/METADATA
indonesian.BMKG-0.17.dist-info/WHEEL
indonesian.BMKG-0.17.dist-info/top_level.txt
indonesian.BMKG-0.17.dist-info/RECORD
