Metadata-Version: 2.1
Name: indonesian.BMKG
Version: 0.17
Summary: this is an package of latest indonesian earthquake
Author: Muhammad Afrizal
Author-email: muhamadafrizal5@gmail.com
Keywords: python,video,stream,video stream,camera stream,sockets
Classifier: Development Status :: 1 - Planning
Classifier: Intended Audience :: Developers
Classifier: Programming Language :: Python :: 3
Classifier: Operating System :: Unix
Classifier: Operating System :: MacOS :: MacOS X
Classifier: Operating System :: Microsoft :: Windows
License-File: LICENSE
Requires-Dist: opencv-python
Requires-Dist: pyautogui
Requires-Dist: pyaudio
